ai_text_utils/__init__.py
ai_text_utils/cli/__init__.py
ai_text_utils/cli/main.py
ai_text_utils/text/__init__.py
ai_text_utils/text/data.py
ai_text_utils/text/datasets.py
ai_text_utils/text/models.py
ai_text_utils/text/utils.py
ai_text_utils-0.1.6.dist-info/METADATA
ai_text_utils-0.1.6.dist-info/WHEEL
ai_text_utils-0.1.6.dist-info/top_level.txt
ai_text_utils-0.1.6.dist-info/RECORD
