Metadata-Version: 2.4
Name: ai-text-utils
Version: 0.1.6
Author-email: kedar <abc@gmail.com>
Requires-Python: >=3.13
Requires-Dist: torch
Requires-Dist: tiktoken
Requires-Dist: numpy
Requires-Dist: beautifulsoup4
Requires-Dist: tqdm
